[
  {
    "icon": "Blog",
    "name": "主页",
    "link": "https://qiecode.top/"
  },
  {
    "icon": "Cloud",
    "name": "AI",
    "link": "https://qiestudy.qiecode.top/"
  },
  {
    "icon": "CompactDisc",
    "name": "音乐",
    "link": "https://app.soundstripe.com/royalty-free-music/"
  },
  {
    "icon": "Compass",
    "name": "头像生成",
    "link": "https://abatar.qiecode.top/"
  },
  {
    "icon": "Book",
    "name": "书本",
    "link": "https://cook.qiecode.top/"
  },
  {
    "icon": "Fire",
    "name": "今日热榜",
    "link": "https://tophub.today/"
  },
  {
    "icon": "LaptopCode",
    "name": "MetaMask",
    "link": "https://metamask.io/"
  }
]
